disparity_interpolation.cpython-38-x86_64-linux-gnu.so
disparity_interpolation-1.0.5.dist-info/LICENSE
disparity_interpolation-1.0.5.dist-info/METADATA
disparity_interpolation-1.0.5.dist-info/top_level.txt
disparity_interpolation-1.0.5.dist-info/RECORD
disparity_interpolation-1.0.5.dist-info/WHEEL
disparity_interpolation.libs/libopencv_imgproc-a7676e93.so.2.4.5
disparity_interpolation.libs/libz-745e0a09.so.1.2.7
disparity_interpolation.libs/libopencv_core-26de4276.so.2.4.5
