Metadata-Version: 2.1
Name: disparity-interpolation
Version: 1.0.5
Summary: Nearest neighbor interpolation for disparity images with missing parts.
Home-page: https://github.com/jhonykaesemodel/disparity_interpolation
Author: Jhony Kaesemodel Pontes
License: UNKNOWN
Platform: UNKNOWN
License-File: LICENSE
